pyeasytd/__init__.py
pyeasytd/file_util.py
pyeasytd/json_util.py
pyeasytd/mysql_util.py
pyeasytd/entries/__init__.py
pyeasytd/entries/json_easy.py
pyeasytd/entries/db/__init__.py
pyeasytd/entries/db/mysql_easy.py
pyeasytd/entries/file/__init__.py
pyeasytd/entries/file/xlsx_file_easy.py
pyeasytd/wechat/__init__.py
pyeasytd-0.0.12.dist-info/LICENSE
pyeasytd-0.0.12.dist-info/METADATA
pyeasytd-0.0.12.dist-info/WHEEL
pyeasytd-0.0.12.dist-info/top_level.txt
pyeasytd-0.0.12.dist-info/zip-safe
pyeasytd-0.0.12.dist-info/RECORD
