Metadata-Version: 2.1
Name: pyeasytd
Version: 0.0.12
Summary: 使Python开发变的更简单
Home-page: https://gitee.com/kingons/pyeasytd
Author: dragons
Author-email: 521274311@qq.com
License: UNKNOWN
Platform: UNKNOWN
Classifier: Intended Audience :: Developers
Classifier: Programming Language :: Python :: 3.7
Classifier: Topic :: Software Development :: Libraries
Requires-Dist: PyMySQL (>=0.9.3)
Requires-Dist: xlrd (>=1.2.0)
Requires-Dist: zmail (>=0.2.8)
Requires-Dist: requests (>=2.22.0)
